LICENSE_GPL
MANIFEST.in
README.rst
setup.cfg
setup.py
bin/ganga
doc/Makefile
doc/conf.py
doc/fill_gpi.py
doc/index.rst
doc/API/index.rst
doc/GPI/index.rst
doc/UserGuide/Configuration.rst
doc/UserGuide/GoogleOauth.rst
doc/UserGuide/InputAndOutputData.rst
doc/UserGuide/InstallAndBasicUsage.rst
doc/UserGuide/JobManipulation.rst
doc/UserGuide/MiscellaneousFunctionality.rst
doc/UserGuide/PostProcessors.rst
doc/UserGuide/Queues.rst
doc/UserGuide/RunningExecutables.rst
doc/UserGuide/Splitters.rst
doc/UserGuide/Tasks.rst
doc/UserGuide/TutorialPlugin.rst
doc/UserGuide/UsingDifferentApplications.rst
doc/UserGuide/UsingDifferentBackends.rst
doc/UserGuide/Virtualization.rst
doc/UserGuide/WhatIsGanga.rst
doc/UserGuide/first_job.gif
doc/UserGuide/index.rst
doc/UserGuide/start_terminal.gif
doc/UserGuide/virtualization.gif
doc/_static/favicon.ico
doc/_static/logo.svg
doc/dev/credentials.rst
doc/dev/index.rst
doc/journal/CPC2007/GangaJob.pdf
doc/journal/CPC2007/GangaOverview.pdf
doc/journal/CPC2007/GangaPlugin.pdf
doc/journal/CPC2007/README
doc/journal/CPC2007/avianflu.pdf
doc/journal/CPC2007/avianflu.png
doc/journal/CPC2007/camtology.tex
doc/journal/CPC2007/camtologyfigure.eps
doc/journal/CPC2007/camtologyfigure.pdf
doc/journal/CPC2007/camtologytech.pdf
doc/journal/CPC2007/elsart.cls
doc/journal/CPC2007/elsart1p.cls
doc/journal/CPC2007/elsart3p.cls
doc/journal/CPC2007/elsart5p.cls
doc/journal/CPC2007/ganga-GUI.eps
doc/journal/CPC2007/ganga-GUI.png
doc/journal/CPC2007/ganga-architecture.png
doc/journal/CPC2007/ganga-architecture.svg
doc/journal/CPC2007/ganga-diane-portal.pdf
doc/journal/CPC2007/ganga-diane-portal.png
doc/journal/CPC2007/ganga-diane-portal.svg
doc/journal/CPC2007/ganga-objects.dia
doc/journal/CPC2007/ganga-objects.eps
doc/journal/CPC2007/ganga-objects.png
doc/journal/CPC2007/ganga.tex
doc/journal/CPC2007/instructions-num.tex
doc/journal/CPC2007/job-uml.dia
doc/journal/CPC2007/job-uml.eps
doc/journal/CPC2007/job-uml.png
doc/journal/CPC2007/monitoring.eps
ganga.egg-info/PKG-INFO
ganga.egg-info/SOURCES.txt
ganga.egg-info/dependency_links.txt
ganga.egg-info/requires.txt
ganga.egg-info/top_level.txt
